graphql_jwt/__init__.py
graphql_jwt/backends.py
graphql_jwt/compat.py
graphql_jwt/decorators.py
graphql_jwt/exceptions.py
graphql_jwt/middleware.py
graphql_jwt/mixins.py
graphql_jwt/mutations.py
graphql_jwt/path.py
graphql_jwt/relay.py
graphql_jwt/settings.py
graphql_jwt/shortcuts.py
graphql_jwt/signals.py
graphql_jwt/testcases.py
graphql_jwt/utils.py
graphql_jwt/refresh_token/__init__.py
graphql_jwt/refresh_token/apps.py
graphql_jwt/refresh_token/decorators.py
graphql_jwt/refresh_token/managers.py
graphql_jwt/refresh_token/mixins.py
graphql_jwt/refresh_token/models.py
graphql_jwt/refresh_token/mutations.py
graphql_jwt/refresh_token/relay.py
graphql_jwt/refresh_token/shortcuts.py
graphql_jwt/refresh_token/signals.py
graphql_jwt/refresh_token/utils.py
graphql_jwt/refresh_token/admin/__init__.py
graphql_jwt/refresh_token/admin/filters.py
graphql_jwt/refresh_token/management/__init__.py
graphql_jwt/refresh_token/management/commands/__init__.py
graphql_jwt/refresh_token/management/commands/cleartokens.py
graphql_jwt/refresh_token/migrations/0001_initial.py
graphql_jwt/refresh_token/migrations/0002_auto_20190130_0900.py
graphql_jwt/refresh_token/migrations/__init__.py
django_graphql_jwt_using_rest_framework_jwt-1.2.0.dist-info/METADATA
django_graphql_jwt_using_rest_framework_jwt-1.2.0.dist-info/WHEEL
django_graphql_jwt_using_rest_framework_jwt-1.2.0.dist-info/top_level.txt
django_graphql_jwt_using_rest_framework_jwt-1.2.0.dist-info/RECORD
