Metadata-Version: 2.1
Name: django-graphql-jwt-using-rest-framework-jwt
Version: 1.2.0
Summary: we use rest-framework-jwt algorithms to implement in django-graphql-jwt
Home-page: UNKNOWN
Author: hieucao192
Author-email: hieucaohd@gmail.com
License: MIT
Platform: UNKNOWN
Classifier: License :: OSI Approved :: MIT License
Classifier: Programming Language :: Python :: 3
Classifier: Programming Language :: Python :: 3.9
Requires-Dist: Django
Requires-Dist: PyJWT
Requires-Dist: djangorestframework-simplejwt
Requires-Dist: graphene-django
